{
    "collectedAtUtc":  "2026-02-14T04:25:34.6013835Z",
    "device":  {
                   "uuid":  "E1F0ABF5-561C-4E5A-BE53-97F7443CA3D9",
                   "manufacturer":  "Microsoft Corporation",
                   "domain":  "WORKGROUP",
                   "serial":  "7096-1621-3984-1564-2534-4015-80",
                   "ramGB":  7.55,
                   "hostname":  "LAB1",
                   "model":  "Virtual Machine"
               },
    "os":  {
               "arch":  "64 bits",
               "lastBoot":  "08/02/2026 7:12:22",
               "name":  "Microsoft Windows Server 2019 Standard",
               "version":  "10.0.17763",
               "build":  "17763"
           },
    "cpu":  [
                {
                    "maxMhz":  2304,
                    "name":  "Intel(R) Core(TM) i7-10610U CPU @ 1.80GHz",
                    "cores":  2,
                    "logical":  4
                }
            ],
    "storage":  [
                    {
                        "deviceId":  "C:",
                        "volumeName":  "",
                        "fs":  "NTFS",
                        "totalGB":  99.4,
                        "usedGB":  93.75,
                        "freeGB":  5.65,
                        "percentUsed":  94.31,
                        "percentFree":  5.69,
                        "percentAvail":  100
                    },
                    {
                        "deviceId":  "D:",
                        "volumeName":  "Data",
                        "fs":  "NTFS",
                        "totalGB":  299.98,
                        "usedGB":  8.36,
                        "freeGB":  291.62,
                        "percentUsed":  2.79,
                        "percentFree":  97.21,
                        "percentAvail":  100
                    }
                ],
    "network":  [
                    {
                        "subnet":  [
                                       "255.255.240.0",
                                       "64"
                                   ],
                        "description":  "Microsoft Hyper-V Network Adapter #3",
                        "gateway":  [
                                        "172.23.96.1"
                                    ],
                        "mac":  "00:15:5D:64:18:06",
                        "ip":  [
                                   "172.23.96.74",
                                   "fe80::4f04:d651:ee4e:332a"
                               ],
                        "dhcpEnabled":  true,
                        "dns":  [
                                    "172.23.96.1"
                                ]
                    },
                    {
                        "subnet":  [
                                       "255.255.255.128",
                                       "64"
                                   ],
                        "description":  "TAP-Windows Adapter V9 for OpenVPN Connect",
                        "gateway":  [
                                        null
                                    ],
                        "mac":  "00:FF:EB:CD:F9:4D",
                        "ip":  [
                                   "192.168.115.3",
                                   "fe80::22a1:9755:d29:5d27"
                               ],
                        "dhcpEnabled":  false,
                        "dns":  [
                                    null
                                ]
                    }
                ],
    "roles":  [
                  "IIS",
                  "SQLServer"
              ],
    "thirdPartyServices":  [
                               {
                                   "name":  "ovpnhelper_service",
                                   "displayName":  "OpenVPN Connect Helper Service",
                                   "state":  "Running",
                                   "startMode":  "Auto",
                                   "startName":  "LocalSystem",
                                   "pathName":  "\"C:\\Program Files\\OpenVPN Connect\\ovpnhelper_service.exe\"",
                                   "exePath":  "C:\\Program Files\\OpenVPN Connect\\ovpnhelper_service.exe",
                                   "company":  null,
                                   "product":  null,
                                   "version":  null
                               },
                               {
                                   "name":  "NWSAPAutoWorkstationUpdateSvc",
                                   "displayName":  "SAPSetup Automatic Workstation Update Service",
                                   "state":  "Running",
                                   "startMode":  "Auto",
                                   "startName":  "LocalSystem",
                                   "pathName":  "\"C:\\Program Files (x86)\\SAP\\SAPsetup\\Setup\\Updater\\NwSapAutoWorkstationUpdateService.exe\"",
                                   "exePath":  "C:\\Program Files (x86)\\SAP\\SAPsetup\\Setup\\Updater\\NwSapAutoWorkstationUpdateService.exe",
                                   "company":  "SAP SE",
                                   "product":  "SAP Front-End Setup for the Windows(R) Environment",
                                   "version":  "9, 0, 106, 0"
                               },
                               {
                                   "name":  "gupdatem",
                                   "displayName":  "Servicio de Google Update (gupdatem)",
                                   "state":  "Stopped",
                                   "startMode":  "Manual",
                                   "startName":  "LocalSystem",
                                   "pathName":  "\"C:\\Program Files (x86)\\Google\\Update\\GoogleUpdate.exe\" /medsvc",
                                   "exePath":  "C:\\Program Files (x86)\\Google\\Update\\GoogleUpdate.exe",
                                   "company":  "Google LLC",
                                   "product":  "Google Updater (x64)",
                                   "version":  "144.0.7547.0"
                               },
                               {
                                   "name":  "TracSrvWrapper",
                                   "displayName":  "Check Point Endpoint Security VPN",
                                   "state":  "Running",
                                   "startMode":  "Auto",
                                   "startName":  "LocalSystem",
                                   "pathName":  "\"C:\\Program Files (x86)\\CheckPoint\\Endpoint Connect\\TracSrvWrapper.exe\"",
                                   "exePath":  "C:\\Program Files (x86)\\CheckPoint\\Endpoint Connect\\TracSrvWrapper.exe",
                                   "company":  "Check Point Software Technologies",
                                   "product":  "trac",
                                   "version":  "5.0"
                               },
                               {
                                   "name":  "CMDBAgent",
                                   "displayName":  "CMDB Agent (Inventory -\u003e GitHub)",
                                   "state":  "Running",
                                   "startMode":  "Auto",
                                   "startName":  "LocalSystem",
                                   "pathName":  "C:\\CMDB\\CMDBAgentService.exe C:\\CMDB\\cmdb-worker.ps1 1800000 C:\\CMDB\\cmdb-agent.log",
                                   "exePath":  "C:\\CMDB\\CMDBAgentService.exe",
                                   "company":  "",
                                   "product":  "",
                                   "version":  "0.0.0.0"
                               },
                               {
                                   "name":  "wgsslvpnsrc",
                                   "displayName":  "WatchGuard SSLVPN Service",
                                   "state":  "Running",
                                   "startMode":  "Auto",
                                   "startName":  "LocalSystem",
                                   "pathName":  "\"C:\\Program Files (x86)\\WatchGuard\\WatchGuard Mobile VPN with SSL\\wgsslvpnsrc.exe\"",
                                   "exePath":  "C:\\Program Files (x86)\\WatchGuard\\WatchGuard Mobile VPN with SSL\\wgsslvpnsrc.exe",
                                   "company":  null,
                                   "product":  null,
                                   "version":  null
                               },
                               {
                                   "name":  "USACARS_API_K",
                                   "displayName":  "USACARS_API_K",
                                   "state":  "Running",
                                   "startMode":  "Auto",
                                   "startName":  "LocalSystem",
                                   "pathName":  "C:\\Tools\\nssm\\nssm.exe",
                                   "exePath":  "C:\\Tools\\nssm\\nssm.exe",
                                   "company":  "",
                                   "product":  "NSSM 64-bit",
                                   "version":  "2.24"
                               },
                               {
                                   "name":  "gupdate",
                                   "displayName":  "Servicio de Google Update (gupdate)",
                                   "state":  "Stopped",
                                   "startMode":  "Auto",
                                   "startName":  "LocalSystem",
                                   "pathName":  "\"C:\\Program Files (x86)\\Google\\Update\\GoogleUpdate.exe\" /svc",
                                   "exePath":  "C:\\Program Files (x86)\\Google\\Update\\GoogleUpdate.exe",
                                   "company":  "Google LLC",
                                   "product":  "Google Updater (x64)",
                                   "version":  "144.0.7547.0"
                               },
                               {
                                   "name":  "EPWD",
                                   "displayName":  "Check Point Endpoint Client Watchdog",
                                   "state":  "Running",
                                   "startMode":  "Auto",
                                   "startName":  "LocalSystem",
                                   "pathName":  "\"C:\\Program Files (x86)\\CheckPoint\\Endpoint Connect\\Watchdog\\EPWD.exe\"",
                                   "exePath":  "C:\\Program Files (x86)\\CheckPoint\\Endpoint Connect\\Watchdog\\EPWD.exe",
                                   "company":  "Check Point Software Technologies Ltd.",
                                   "product":  "End Point Security R80",
                                   "version":  "868650002"
                               },
                               {
                                   "name":  "CosmosUpdater",
                                   "displayName":  "CosmosUpdater",
                                   "state":  "Running",
                                   "startMode":  "Manual",
                                   "startName":  "LocalSystem",
                                   "pathName":  "\"C:\\Program Files\\Chaos\\Cosmos\\cbservice.exe\" updater",
                                   "exePath":  "C:\\Program Files\\Chaos\\Cosmos\\cbservice.exe",
                                   "company":  "ChaosGroup",
                                   "product":  "Chaos Cosmos Browser",
                                   "version":  "2025.05.28-543606"
                               },
                               {
                                   "name":  "agent_ovpnconnect",
                                   "displayName":  "OpenVPN Agent agent_ovpnconnect",
                                   "state":  "Running",
                                   "startMode":  "Auto",
                                   "startName":  "LocalSystem",
                                   "pathName":  "\"C:\\Program Files\\OpenVPN Connect\\agent_ovpnconnect.exe\"",
                                   "exePath":  "C:\\Program Files\\OpenVPN Connect\\agent_ovpnconnect.exe",
                                   "company":  null,
                                   "product":  null,
                                   "version":  null
                               },
                               {
                                   "name":  "FA_Scheduler",
                                   "displayName":  "FortiClient VPN Service Scheduler",
                                   "state":  "Running",
                                   "startMode":  "Auto",
                                   "startName":  "LocalSystem",
                                   "pathName":  "\"C:\\Program Files\\Fortinet\\FortiClient\\scheduler.exe\"",
                                   "exePath":  "C:\\Program Files\\Fortinet\\FortiClient\\scheduler.exe",
                                   "company":  "Fortinet Inc.",
                                   "product":  "FortiClient Scheduler",
                                   "version":  "7.4.3.1790"
                               },
                               {
                                   "name":  "GoogleUpdaterService144.0.7547.0",
                                   "displayName":  "Servicio de herramienta de actualización de Google (GoogleUpdaterService144.0.7547.0)",
                                   "state":  "Stopped",
                                   "startMode":  "Auto",
                                   "startName":  "LocalSystem",
                                   "pathName":  "\"C:\\Program Files (x86)\\Google\\GoogleUpdater\\144.0.7547.0\\updater.exe\" --system --windows-service --service=update",
                                   "exePath":  "C:\\Program Files (x86)\\Google\\GoogleUpdater\\144.0.7547.0\\updater.exe",
                                   "company":  "Google LLC",
                                   "product":  "Google Updater (x64)",
                                   "version":  "144.0.7547.0"
                               },
                               {
                                   "name":  "GoogleUpdaterInternalService144.0.7547.0",
                                   "displayName":  "Servicio interno de la herramienta de actualización de Google (GoogleUpdaterInternalService144.0.7547.0)",
                                   "state":  "Stopped",
                                   "startMode":  "Auto",
                                   "startName":  "LocalSystem",
                                   "pathName":  "\"C:\\Program Files (x86)\\Google\\GoogleUpdater\\144.0.7547.0\\updater.exe\" --system --windows-service --service=update-internal",
                                   "exePath":  "C:\\Program Files (x86)\\Google\\GoogleUpdater\\144.0.7547.0\\updater.exe",
                                   "company":  "Google LLC",
                                   "product":  "Google Updater (x64)",
                                   "version":  "144.0.7547.0"
                               },
                               {
                                   "name":  "GoogleChromeElevationService",
                                   "displayName":  "Google Chrome Elevation Service (GoogleChromeElevationService)",
                                   "state":  "Stopped",
                                   "startMode":  "Manual",
                                   "startName":  "LocalSystem",
                                   "pathName":  "\"C:\\Program Files\\Google\\Chrome\\Application\\144.0.7559.133\\elevation_service.exe\"",
                                   "exePath":  "C:\\Program Files\\Google\\Chrome\\Application\\144.0.7559.133\\elevation_service.exe",
                                   "company":  "Google LLC",
                                   "product":  "Google Chrome",
                                   "version":  "144.0.7559.133"
                               }
                           ],
    "virtualization":  {
                           "hypervisorVendor":  "Hyper-V",
                           "manufacturer":  "Microsoft Corporation",
                           "model":  "Virtual Machine",
                           "physicalHostName":  "RDIAZM-K.kionetworks.com",
                           "source":  "registry(HKLM:\\\\SOFTWARE\\\\Microsoft\\\\Virtual Machine\\\\Guest\\\\Parameters\\\\HostName)"
                       },
    "capacityVsUsage":  {
                            "cpu":  {
                                        "percentUsed":  7,
                                        "percentAvailable":  100,
                                        "collectedAtUtc":  "2026-02-14T04:25:38.2115784Z"
                                    },
                            "ram":  {
                                        "totalGB":  7.55,
                                        "usedGB":  5.37,
                                        "freeGB":  2.18,
                                        "percentUsed":  71.14,
                                        "percentFree":  28.86,
                                        "percentAvail":  100,
                                        "collectedAtUtc":  "2026-02-14T04:25:38.2539807Z"
                                    },
                            "diskSummary":  {
                                                "totalGB":  399.38,
                                                "usedGB":  102.11,
                                                "freeGB":  297.27,
                                                "percentUsed":  25.57,
                                                "percentAvail":  100
                                            }
                        }
}